db/__init__.py
mob_suite/__init__.py
mob_suite/config.json
mob_suite/constants.py
mob_suite/mob_cluster.py
mob_suite/mob_init.py
mob_suite/mob_recon.py
mob_suite/mob_typer.py
mob_suite/utils.py
mob_suite/version.py
mob_suite/blast/__init__.py
mob_suite/classes/__init__.py
mob_suite/databases/__init__.py
mob_suite/example/AB040415.fasta
mob_suite/example/SRR3703080_illumina_unicycler.fasta
mob_suite/example/assembly_no_biomarkers.fasta
mob_suite/tests/test_mob_init.py
mob_suite/tests/test_mobrecon.py
mob_suite/tests/test_mobtyper.py
mob_suite/tests/test_mobtyper_vs_biomarker_report.py
mob_suite/tests/TestData/AB011548.fasta
mob_suite/tests/TestData/AB040415.fasta
mob_suite/tests/TestData/AY603981.fasta
mob_suite/tests/TestData/KU295134.fasta
mob_suite/tests/TestData/KX377410.fasta
mob_suite/tests/TestData/NC_011385.1.fasta
mob_suite/tests/TestData/pCAV1453-208.fasta
mob_suite/wrappers/__init__.py
mob_suite-3.1.9.dist-info/LICENSE
mob_suite-3.1.9.dist-info/METADATA
mob_suite-3.1.9.dist-info/WHEEL
mob_suite-3.1.9.dist-info/entry_points.txt
mob_suite-3.1.9.dist-info/top_level.txt
mob_suite-3.1.9.dist-info/RECORD
