Metadata-Version: 2.1
Name: mob-suite
Version: 3.1.9
Summary: MOB-suite is a set of tools for finding, typing and reconstruction of plasmids from draft and complete genome assemblies.
Home-page: https://github.com/phac-nml/mob-suite
Author: James Robertson
Author-email: james.robertson@canada.ca
License: GPLv3
Keywords: Plasmids finding typing reconstruction
Classifier: Development Status :: 3 - Alpha
Classifier: Environment :: Console
Classifier: License :: OSI Approved :: Apache Software License
Classifier: Intended Audience :: Science/Research
Classifier: Topic :: Scientific/Engineering
Classifier: Topic :: Scientific/Engineering :: Bio-Informatics
Classifier: Programming Language :: Python
Classifier: Programming Language :: Python :: 3.7
Classifier: Programming Language :: Python :: 3.8
Classifier: Programming Language :: Python :: Implementation :: CPython
Classifier: Operating System :: POSIX :: Linux
Requires-Python: >=3.7.0,<4
License-File: LICENSE
Requires-Dist: numpy <1.23.5,>=1.11.1
Requires-Dist: tables <4,>=3.3.0
Requires-Dist: pandas <=1.5.3,>=0.22.0
Requires-Dist: biopython <2,>=1.8
Requires-Dist: pycurl <8,>=7.43.0
Requires-Dist: scipy <2,>=1.1.0
Requires-Dist: ete3 <4,>=3.1.3
Requires-Dist: six <2,>=1.10
